dbt2pdf/__init__.py
dbt2pdf/__main__.py
dbt2pdf/cli.py
dbt2pdf/font.py
dbt2pdf/logger.py
dbt2pdf/manifest.py
dbt2pdf/pdf.py
dbt2pdf/schemas.py
dbt2pdf/utils.py
dbt2pdf/warnings.py
dbt2pdf-0.1.1.dist-info/METADATA
dbt2pdf-0.1.1.dist-info/WHEEL
dbt2pdf-0.1.1.dist-info/entry_points.txt
dbt2pdf-0.1.1.dist-info/licenses/LICENSE
dbt2pdf-0.1.1.dist-info/RECORD
