Metadata-Version: 2.4
Name: dbt2pdf
Version: 0.1.1
Summary: Generate a PDF document from your DBT project's documentation.
Project-URL: Homepage, https://github.com/dribia/dbt2pdf
Project-URL: Repository, https://github.com/dribia/dbt2pdf
Author-email: Dribia Code <code@dribia.com>
Maintainer-email: Dribia Code <code@dribia.com>
License-Expression: MIT
License-File: LICENSE
Keywords: dbt,docs,documentation,pdf
Classifier: Development Status :: 2 - Pre-Alpha
Classifier: Intended Audience :: Developers
Classifier: Intended Audience :: Information Technology
Classifier: License :: OSI Approved :: MIT License
Classifier: Natural Language :: English
Classifier: Operating System :: OS Independent
Classifier: Programming Language :: Python :: 3 :: Only
Classifier: Programming Language :: Python :: 3.9
Classifier: Programming Language :: Python :: 3.10
Classifier: Programming Language :: Python :: 3.11
Classifier: Programming Language :: Python :: 3.12
Classifier: Programming Language :: Python :: 3.13
Classifier: Programming Language :: Python :: 3.14
Classifier: Topic :: Database
Classifier: Topic :: Documentation
Classifier: Topic :: Software Development :: Documentation
Classifier: Typing :: Typed
Requires-Python: <3.15,>=3.10
Requires-Dist: fpdf2<3,>=2.7.9
Requires-Dist: matplotlib<4,>=3.9.2
Requires-Dist: pydantic<3.0,>=1.10
Requires-Dist: rich<15,>=14.1.0
Requires-Dist: typer<0.22,>=0.20.0
